FSM/fsm_prob.v
module fsm_prob(output reg clk,
                output reg reset,
                output reg init,
                output reg [4:0] main_fifo_low,
                output reg [4:0] main_fifo_high,
                output reg [4:0] Vco_low,
                output reg [4:0] Vco_high,
                output reg [4:0] Vc1_low, 
                output reg [4:0] Vc1_high,
                output reg [4:0] Do_low,
                output reg [4:0] Do_high,
                output reg [4:0] D1_low,
                output reg [4:0] D1_high, 
                output reg [4:0]empties,
                output reg [4:0]errors 
                );

    initial begin
        $dumpfile("fsm.vcd");
        $dumpvars;
        {empties, reset, errors, init, main_fifo_low, main_fifo_high, Vco_low, Vco_high, Vc1_low, Vc1_high, Do_low, Do_high, D1_low, D1_high} <=0;
        @(posedge clk); 
        reset <= 1;
        @(posedge clk);
        main_fifo_low<='h3;
        Vc1_low<='hA;
        Vco_low<='hB;
        Do_low<='hC;
        D1_low<='hD;
        @(posedge clk);
        init<=0;
        main_fifo_high<='h6;
        Vc1_high<='h7;
        Vco_high<='h8;
        Do_high<='h9;
        D1_high<='hA;
        @(posedge clk);
        @(posedge clk);
        empties <= 1;
        @(posedge clk);
        {main_fifo_low, main_fifo_high, Vco_low, Vco_high, Vc1_low, Vc1_high, Do_low, Do_high, D1_low, D1_high} <=0;
        @(posedge clk);
        errors <=1;
        @(posedge clk);
        @(posedge clk);
        reset<=0;
        @(posedge clk);
        reset<=1;
        @(posedge clk);
        @(posedge clk);
        @(posedge clk);
        $finish;
    end



    initial clk <=0;
    always #2 clk <= ~clk;


endmodule

FSM/fsm.v
module fsm (
    input clk, 
    input reset, 
    input init,
    input [4:0] main_fifo_low,
    input [4:0] main_fifo_high,
    input [4:0] Vco_low,
    input [4:0] Vco_high,
    input [4:0] Vc1_low, 
    input [4:0] Vc1_high,
    input [4:0] Do_low,
    input [4:0] Do_high,
    input [4:0] D1_low,
    input [4:0] D1_high, 
    input [4:0] empties,
    input [4:0]errors, 
    output reg error_out, 
    output reg active_out, 
    output reg idle_out, 
    output reg  [4:0] mf_l,
    output reg  [4:0] mf_h,
    output reg  [4:0] vco_l,
    output reg  [4:0] vco_h,
    output reg  [4:0] vc1_l,
    output reg  [4:0] vc1_h,
    output reg  [4:0] do_l,
    output reg  [4:0] do_h,
    output reg  [4:0] d1_l,
    output reg  [4:0] d1_h

); 


parameter SIZE = 5;
parameter RESET = 5'b00001; //1
parameter INIT = 5'b00010;  //2
parameter IDLE = 5'b00100;  //4
parameter ACTIVE = 5'b01000; //8
parameter ERROR = 5'b10000; //16

reg [SIZE-1:0]  state;
reg [SIZE-1:0]  next_state;
reg lol;


always @(posedge clk) begin
	if (~reset) begin 
		state <= RESET; 
        lol<=0;
	end else begin 
		state <= next_state;  
        if(state == RESET) begin
            {mf_l,mf_h,vco_l,vco_h,vc1_l,vc1_h,do_l,do_h,d1_l,d1_h} <= 0;

        end
        if(state == INIT) begin
            mf_l <= main_fifo_low;
            mf_h <= main_fifo_high;
            vco_l <= Vco_low;
            vco_h <= Vco_high;
            vc1_l <= Vc1_low;
            vc1_h <= Vc1_high;
            do_l <= Do_low;
            do_h <= Do_high;
            d1_l <= D1_low;
            d1_h <= D1_high;
        end
	end


end

always @(*) begin 
    next_state=state;
    error_out=0; 
    idle_out=0; 
    active_out=0; 

    case(state)
    
        RESET: begin 

            if(reset==1)begin 
                next_state=INIT; 
            end else if(reset==1 && init==1) begin 
                next_state=INIT; 
            end 
        end 


        INIT: begin 

            if(init==0) begin 
                next_state=IDLE; 
            end else begin 
                next_state=INIT; 
            end 
        end 


        IDLE: begin 
             
            if(init)
                next_state=INIT; 
            else begin
                if(empties==0) begin //si todos empties 
                    idle_out=1;  //esta esperando 
                    next_state=IDLE; 
                end else begin //nada más espera si no
                    idle_out=0;     
                    next_state=ACTIVE; 
                end

            end   
        end 


        ACTIVE: begin 
             
            if (init) begin
                next_state=INIT;
            end else begin
                if(errors[4:0]==0)begin 
                    next_state=ACTIVE;
                    active_out=1;     
                end else if(errors[4:0]>=1) begin 
                    next_state=ERROR;
                    active_out=0; 
                end

            end   
        end 


        ERROR: begin  
            if(reset==0)begin 
                next_state=RESET;
                error_out=0; 
            end else begin 
                next_state=ERROR;
                error_out=1; 
                end 
        end 

        default: begin
            next_state=RESET; 

        end
        
    endcase   
end 




endmodule

FSM/fsm_tb.v
`include "fsm.v"
`include "fsm_prob.v"


module fsm_tb; 


    /*AUTOWIRE*/
    // Beginning of automatic wires (for undeclared instantiated-module outputs)
    wire [4:0]		D1_high;		// From master of fsm_prob.v
    wire [4:0]		D1_low;			// From master of fsm_prob.v
    wire [4:0]		Do_high;		// From master of fsm_prob.v
    wire [4:0]		Do_low;			// From master of fsm_prob.v
    wire [4:0]		Vc1_high;		// From master of fsm_prob.v
    wire [4:0]		Vc1_low;		// From master of fsm_prob.v
    wire [4:0]		Vco_high;		// From master of fsm_prob.v
    wire [4:0]		Vco_low;		// From master of fsm_prob.v
    wire		active_out;		// From slave of fsm.v
    wire		clk;			// From master of fsm_prob.v
    wire [4:0]		d1_h;			// From slave of fsm.v
    wire [4:0]		d1_l;			// From slave of fsm.v
    wire [4:0]		do_h;			// From slave of fsm.v
    wire [4:0]		do_l;			// From slave of fsm.v
    wire [4:0]		empties;		// From master of fsm_prob.v
    wire		error_out;		// From slave of fsm.v
    wire [4:0]		errors;			// From master of fsm_prob.v
    wire		idle_out;		// From slave of fsm.v
    wire		init;			// From master of fsm_prob.v
    wire [4:0]		main_fifo_high;		// From master of fsm_prob.v
    wire [4:0]		main_fifo_low;		// From master of fsm_prob.v
    wire [4:0]		mf_h;			// From slave of fsm.v
    wire [4:0]		mf_l;			// From slave of fsm.v
    wire		reset;			// From master of fsm_prob.v
    wire [4:0]		vc1_h;			// From slave of fsm.v
    wire [4:0]		vc1_l;			// From slave of fsm.v
    wire [4:0]		vco_h;			// From slave of fsm.v
    wire [4:0]		vco_l;			// From slave of fsm.v
    // End of automatics
   
    fsm slave(/*AUTOINST*/
	      // Outputs
	      .error_out		(error_out),
	      .active_out		(active_out),
	      .idle_out			(idle_out),
	      .mf_l			(mf_l[4:0]),
	      .mf_h			(mf_h[4:0]),
	      .vco_l			(vco_l[4:0]),
	      .vco_h			(vco_h[4:0]),
	      .vc1_l			(vc1_l[4:0]),
	      .vc1_h			(vc1_h[4:0]),
	      .do_l			(do_l[4:0]),
	      .do_h			(do_h[4:0]),
	      .d1_l			(d1_l[4:0]),
	      .d1_h			(d1_h[4:0]),
	      // Inputs
	      .clk			(clk),
	      .reset			(reset),
	      .init			(init),
	      .main_fifo_low		(main_fifo_low[4:0]),
	      .main_fifo_high		(main_fifo_high[4:0]),
	      .Vco_low			(Vco_low[4:0]),
	      .Vco_high			(Vco_high[4:0]),
	      .Vc1_low			(Vc1_low[4:0]),
	      .Vc1_high			(Vc1_high[4:0]),
	      .Do_low			(Do_low[4:0]),
	      .Do_high			(Do_high[4:0]),
	      .D1_low			(D1_low[4:0]),
	      .D1_high			(D1_high[4:0]),
	      .empties			(empties[4:0]),
	      .errors			(errors[4:0]));

    fsm_prob master(/*AUTOINST*/
		    // Outputs
		    .clk		(clk),
		    .reset		(reset),
		    .init		(init),
		    .main_fifo_low	(main_fifo_low[4:0]),
		    .main_fifo_high	(main_fifo_high[4:0]),
		    .Vco_low		(Vco_low[4:0]),
		    .Vco_high		(Vco_high[4:0]),
		    .Vc1_low		(Vc1_low[4:0]),
		    .Vc1_high		(Vc1_high[4:0]),
		    .Do_low		(Do_low[4:0]),
		    .Do_high		(Do_high[4:0]),
		    .D1_low		(D1_low[4:0]),
		    .D1_high		(D1_high[4:0]),
		    .empties		(empties[4:0]),
		    .errors		(errors[4:0]));
    





endmodule

FSM/fsm.vcd
$date
	Fri Jun 21 19:46:51 2019
$end
$version
	Icarus Verilog
$end
$timescale
	1s
$end
$scope module fsm_tb $end
$var wire 5 ! vco_l [4:0] $end
$var wire 5 " vco_h [4:0] $end
$var wire 5 # vc1_l [4:0] $end
$var wire 5 $ vc1_h [4:0] $end
$var wire 1 % reset $end
$var wire 5 & mf_l [4:0] $end
$var wire 5 ' mf_h [4:0] $end
$var wire 5 ( main_fifo_low [4:0] $end
$var wire 5 ) main_fifo_high [4:0] $end
$var wire 1 * init $end
$var wire 1 + idle_out $end
$var wire 5 , errors [4:0] $end
$var wire 1 - error_out $end
$var wire 5 . empties [4:0] $end
$var wire 5 / do_l [4:0] $end
$var wire 5 0 do_h [4:0] $end
$var wire 5 1 d1_l [4:0] $end
$var wire 5 2 d1_h [4:0] $end
$var wire 1 3 clk $end
$var wire 1 4 active_out $end
$var wire 5 5 Vco_low [4:0] $end
$var wire 5 6 Vco_high [4:0] $end
$var wire 5 7 Vc1_low [4:0] $end
$var wire 5 8 Vc1_high [4:0] $end
$var wire 5 9 Do_low [4:0] $end
$var wire 5 : Do_high [4:0] $end
$var wire 5 ; D1_low [4:0] $end
$var wire 5 < D1_high [4:0] $end
$scope module master $end
$var reg 5 = D1_high [4:0] $end
$var reg 5 > D1_low [4:0] $end
$var reg 5 ? Do_high [4:0] $end
$var reg 5 @ Do_low [4:0] $end
$var reg 5 A Vc1_high [4:0] $end
$var reg 5 B Vc1_low [4:0] $end
$var reg 5 C Vco_high [4:0] $end
$var reg 5 D Vco_low [4:0] $end
$var reg 1 3 clk $end
$var reg 5 E empties [4:0] $end
$var reg 5 F errors [4:0] $end
$var reg 1 * init $end
$var reg 5 G main_fifo_high [4:0] $end
$var reg 5 H main_fifo_low [4:0] $end
$var reg 1 % reset $end
$upscope $end
$scope module slave $end
$var wire 5 I D1_high [4:0] $end
$var wire 5 J D1_low [4:0] $end
$var wire 5 K Do_high [4:0] $end
$var wire 5 L Do_low [4:0] $end
$var wire 5 M Vc1_high [4:0] $end
$var wire 5 N Vc1_low [4:0] $end
$var wire 5 O Vco_high [4:0] $end
$var wire 5 P Vco_low [4:0] $end
$var wire 1 3 clk $end
$var wire 5 Q empties [4:0] $end
$var wire 5 R errors [4:0] $end
$var wire 1 * init $end
$var wire 5 S main_fifo_high [4:0] $end
$var wire 5 T main_fifo_low [4:0] $end
$var wire 1 % reset $end
$var reg 1 4 active_out $end
$var reg 5 U d1_h [4:0] $end
$var reg 5 V d1_l [4:0] $end
$var reg 5 W do_h [4:0] $end
$var reg 5 X do_l [4:0] $end
$var reg 1 - error_out $end
$var reg 1 + idle_out $end
$var reg 1 Y lol $end
$var reg 5 Z mf_h [4:0] $end
$var reg 5 [ mf_l [4:0] $end
$var reg 5 \ next_state [4:0] $end
$var reg 5 ] state [4:0] $end
$var reg 5 ^ vc1_h [4:0] $end
$var reg 5 _ vc1_l [4:0] $end
$var reg 5 ` vco_h [4:0] $end
$var reg 5 a vco_l [4:0] $end
$upscope $end
$upscope $end
$enddefinitions $end
#0
$dumpvars
bx a
bx `
bx _
bx ^
bx ]
b1 \
bx [
bx Z
xY
bx X
bx W
bx V
bx U
b0 T
b0 S
b0 R
b0 Q
b0 P
b0 O
b0 N
b0 M
b0 L
b0 K
b0 J
b0 I
b0 H
b0 G
b0 F
b0 E
b0 D
b0 C
b0 B
b0 A
b0 @
b0 ?
b0 >
b0 =
b0 <
b0 ;
b0 :
b0 9
b0 8
b0 7
b0 6
b0 5
04
03
bx 2
bx 1
bx 0
bx /
b0 .
0-
b0 ,
0+
0*
b0 )
b0 (
bx '
bx &
0%
bx $
bx #
bx "
bx !
$end
#2
b10 \
0Y
b1 ]
1%
13
#4
03
#6
b100 \
b1101 ;
b1101 >
b1101 J
b1100 9
b1100 @
b1100 L
b1011 5
b1011 D
b1011 P
b1010 7
b1010 B
b1010 N
b11 (
b11 H
b11 T
b0 &
b0 [
b0 '
b0 Z
b0 !
b0 a
b0 "
b0 `
b0 #
b0 _
b0 $
b0 ^
b0 /
b0 X
b0 0
b0 W
b0 1
b0 V
b0 2
b0 U
b10 ]
13
#8
03
#10
1+
b1101 1
b1101 V
b1100 /
b1100 X
b1010 #
b1010 _
b1011 !
b1011 a
b11 &
b11 [
b100 ]
b1010 <
b1010 =
b1010 I
b1001 :
b1001 ?
b1001 K
b1000 6
b1000 C
b1000 O
b111 8
b111 A
b111 M
b110 )
b110 G
b110 S
13
#12
03
#14
13
#16
03
#18
b1000 \
0+
b1 .
b1 E
b1 Q
13
#20
03
#22
14
b0 (
b0 H
b0 T
b0 )
b0 G
b0 S
b0 5
b0 D
b0 P
b0 6
b0 C
b0 O
b0 7
b0 B
b0 N
b0 8
b0 A
b0 M
b0 9
b0 @
b0 L
b0 :
b0 ?
b0 K
b0 ;
b0 >
b0 J
b0 <
b0 =
b0 I
b1000 ]
13
#24
03
#26
b10000 \
04
b1 ,
b1 F
b1 R
13
#28
03
#30
1-
b10000 ]
13
#32
03
#34
b1 \
0-
0%
13
#36
03
#38
b10 \
1%
b1 ]
13
#40
03
#42
b100 \
b0 &
b0 [
b0 !
b0 a
b0 #
b0 _
b0 /
b0 X
b0 1
b0 V
b10 ]
13
#44
03
#46
b1000 \
b100 ]
13
#48
03
#50
b10000 \
b1000 ]
13
